hyper_fetch/__init__.py
hyper_fetch/__version__.py
hyper_fetch/downloader.py
hyper_fetch/types.py
hyper_fetch/caching/__init__.py
hyper_fetch/caching/base.py
hyper_fetch/caching/db.py
hyper_fetch/caching/disk.py
hyper_fetch/caching/memory.py
hyper_fetch/plugins/__init__.py
hyper_fetch/plugins/compression.py
hyper_fetch/plugins/websocket.py
hyper_fetch/rate_limiter/__init__.py
hyper_fetch/rate_limiter/base.py
hyper_fetch/rate_limiter/token_bucket.py
hyperfetch_py-0.0.1a0.dist-info/METADATA
hyperfetch_py-0.0.1a0.dist-info/WHEEL
hyperfetch_py-0.0.1a0.dist-info/licenses/LICENSE
hyperfetch_py-0.0.1a0.dist-info/RECORD
