Metadata-Version: 2.4
Name: hyperfetch-py
Version: 0.0.1a0
Summary: High-performance, async, parallel HTTP downloader for Python 3
Project-URL: Homepage, https://github.com/masroore/hyper_fetch.py
Project-URL: Issues, https://github.com/masroore/hyper_fetch.py/issues
Author-email: Masroor Ehsan <masroore@gmail.com>
License-Expression: MIT
License-File: LICENSE
Classifier: Operating System :: OS Independent
Classifier: Programming Language :: Python :: 3
Classifier: Programming Language :: Python :: 3.12
Classifier: Programming Language :: Python :: 3.13
Requires-Python: >=3.12
Requires-Dist: aiofiles>=24.1.0
Requires-Dist: asyncio
Requires-Dist: brotli>=1.1.0
Requires-Dist: build>=1.2.2.post1
Requires-Dist: click>=8.1.8
Requires-Dist: httpx[socks]>=0.28.1
Requires-Dist: twine>=6.1.0
Requires-Dist: zstandard>=0.23.0
